TkToolTip/TkToolTip.py
TkToolTip/__init__.py
TkToolTip-1.2.0.dist-info/LICENSE
TkToolTip-1.2.0.dist-info/METADATA
TkToolTip-1.2.0.dist-info/WHEEL
TkToolTip-1.2.0.dist-info/top_level.txt
TkToolTip-1.2.0.dist-info/RECORD
