Metadata-Version: 2.1
Name: TkToolTip
Version: 1.2.0
Summary: A sophisticated ToolTip library for Tkinter
Home-page: https://github.com/seuusuario/TkToolTip
Author: Claudio Morais
Author-email: jc.morais86@gmail.com
Classifier: Programming Language :: Python :: 3
Classifier: License :: OSI Approved :: MIT License
Classifier: Operating System :: OS Independent
Requires-Python: >=3.6
License-File: LICENSE
